README.md
setup.py
dunder_mifflin/__init__.py
dunder_mifflin/office_opening.py
dunder_mifflin/screen.py
dunder_mifflin.egg-info/PKG-INFO
dunder_mifflin.egg-info/SOURCES.txt
dunder_mifflin.egg-info/dependency_links.txt
dunder_mifflin.egg-info/not-zip-safe
dunder_mifflin.egg-info/requires.txt
dunder_mifflin.egg-info/top_level.txt